safegraph_eval/__init__.py
safegraph_eval/geometry/__init__.py
safegraph_eval/geometry/geometry.py
safegraph_eval/ingest/__init__.py
safegraph_eval/ingest/ingest.py
safegraph_eval/plotting/__init__.py
safegraph_eval/plotting/plotting.py
safegraph_eval/preprocessing/__init__.py
safegraph_eval/preprocessing/preprocessing.py
safegraph_eval-0.1.2.dist-info/LICENSE
safegraph_eval-0.1.2.dist-info/METADATA
safegraph_eval-0.1.2.dist-info/WHEEL
safegraph_eval-0.1.2.dist-info/top_level.txt
safegraph_eval-0.1.2.dist-info/RECORD
